fastapi_security/__init__.py
fastapi_security/api.py
fastapi_security/basic.py
fastapi_security/entities.py
fastapi_security/exceptions.py
fastapi_security/oauth2.py
fastapi_security/oidc.py
fastapi_security/permissions.py
fastapi_security/schemes.py
fastapi_security-0.4.0.dist-info/LICENSE
fastapi_security-0.4.0.dist-info/WHEEL
fastapi_security-0.4.0.dist-info/METADATA
fastapi_security-0.4.0.dist-info/RECORD
