Metadata-Version: 2.1
Name: fastapi-security
Version: 0.4.0
Summary: Add authentication and authorization to your FastAPI app via dependencies.
Home-page: https://jmagnusson.github.io/fastapi-security/
License: MIT
Author: Jacob Magnusson
Author-email: m@jacobian.se
Requires-Python: >=3.6,<4.0
Classifier: Development Status :: 4 - Beta
Classifier: Environment :: Web Environment
Classifier: Framework :: AsyncIO
Classifier: Intended Audience :: Developers
Classifier: Intended Audience :: Information Technology
Classifier: Intended Audience :: System Administrators
Classifier: License :: OSI Approved :: MIT License
Classifier: Operating System :: OS Independent
Classifier: Programming Language :: Python
Classifier: Programming Language :: Python :: 3
Classifier: Programming Language :: Python :: 3 :: Only
Classifier: Programming Language :: Python :: 3.6
Classifier: Programming Language :: Python :: 3.7
Classifier: Programming Language :: Python :: 3.8
Classifier: Programming Language :: Python :: 3.9
Classifier: Topic :: Internet
Classifier: Topic :: Internet :: WWW/HTTP
Classifier: Topic :: Software Development
Classifier: Topic :: Software Development :: Libraries
Classifier: Topic :: Software Development :: Libraries :: Python Modules
Classifier: Typing :: Typed
Requires-Dist: PyJWT[crypto] (>=2,<3)
Requires-Dist: aiohttp (>=3,<4)
Requires-Dist: fastapi (>=0,<1)
Requires-Dist: pydantic (>=1,<2)
Project-URL: Documentation, https://jmagnusson.github.io/fastapi-security/
Project-URL: Repository, https://github.com/jmagnusson/fastapi-security
